{
    "header": [
        "order id",
        "user",
        "total price",
        "phone",
        "date",
        "status"
    ],
    "body": [
        {
            "id": "#OD1711",
            "user": "john doe",
            "date": "17 Jun 2021",
            "price": "$900",
            "phone": "0522982504",
            "status": "shipping"
        },
        {
            "id": "#OD1712",
            "user": "frank iva",
            "date": "1 Jun 2021",
            "price": "$400",
            "phone": "0522982504",
            "status": "paid"
        },
        {
            "id": "#OD1713",
            "user": "anthony baker",
            "date": "27 Jun 2021",
            "price": "$200",
            "phone": "0522982504",
            "status": "pending"
        },
        {
            "id": "#OD1712",
            "user": "frank iva",
            "date": "1 Jun 2021",
            "price": "$400",
            "phone": "0522982504",
            "status": "paid"
        },
        {
            "id": "#OD1713",
            "user": "anthony baker",
            "date": "27 Jun 2021",
            "price": "$200",
            "phone": "0522982504",
            "status": "refund"
        },
        {
            "id": "#OD1713",
            "user": "anthony baker",
            "date": "27 Jun 2021",
            "price": "$200",
            "phone": "0522982504",
            "status": "refund"
        },
        {
            "id": "#OD1713",
            "user": "anthony baker",
            "date": "27 Jun 2021",
            "price": "$200",
            "phone": "0522982504",
            "status": "refund"
        },
        {
            "id": "#OD1713",
            "user": "anthony baker",
            "date": "27 Jun 2021",
            "price": "$200",
            "phone": "0522982504",
            "status": "refund"
        },
        {
            "id": "#OD1713",
            "user": "anthony baker",
            "date": "27 Jun 2021",
            "price": "$200",
            "phone": "0522982504",
            "status": "refund"
        }
    ]
}